revproxy/__init__.py
revproxy/apps.py
revproxy/connection.py
revproxy/exceptions.py
revproxy/response.py
revproxy/settings.py
revproxy/transformer.py
revproxy/utils.py
revproxy/views.py
django_revproxy-0.13.0.dist-info/LICENSE
django_revproxy-0.13.0.dist-info/METADATA
django_revproxy-0.13.0.dist-info/WHEEL
django_revproxy-0.13.0.dist-info/top_level.txt
django_revproxy-0.13.0.dist-info/RECORD
