Metadata-Version: 2.1
Name: django-revproxy
Version: 0.13.0
Summary: Yet another Django reverse proxy application
Author-email: Sergio Oliveira <sergio@tracy.com.br>
License: MPL v2.0
Project-URL: homepage, https://github.com/jazzband/django-revproxy
Project-URL: download, https://pypi.org/project/django-revproxy/
Project-URL: documentation, https://django-revproxy.readthedocs.io/en/stable/
Project-URL: changelog, https://django-revproxy.readthedocs.io/en/latest/changelog.html
Project-URL: issues, https://github.com/jazzband/django-revproxy/issues
Keywords: django,reverse proxy,revproxy
Classifier: Development Status :: 5 - Production/Stable
Classifier: Environment :: Web Environment
Classifier: Framework :: Django
Classifier: Intended Audience :: Developers
Classifier: License :: OSI Approved :: Mozilla Public License 2.0 (MPL 2.0)
Classifier: Operating System :: OS Independent
Classifier: Programming Language :: Python
Classifier: Programming Language :: Python :: 3.7
Classifier: Programming Language :: Python :: 3.8
Classifier: Programming Language :: Python :: 3.9
Classifier: Programming Language :: Python :: 3.10
Classifier: Programming Language :: Python :: 3.11
Classifier: Framework :: Django
Classifier: Framework :: Django :: 3.0
Classifier: Framework :: Django :: 3.1
Classifier: Framework :: Django :: 3.2
Classifier: Framework :: Django :: 4.0
Classifier: Framework :: Django :: 4.1
Classifier: Framework :: Django :: 4.2
Classifier: Programming Language :: Python :: Implementation :: CPython
Classifier: Programming Language :: Python :: Implementation :: PyPy
Classifier: Topic :: Internet :: Proxy Servers
Classifier: Topic :: Internet :: WWW/HTTP
Classifier: Topic :: Software Development :: Libraries
Requires-Python: >=3.7
License-File: LICENSE
Requires-Dist: Django>=3.0
Requires-Dist: urllib3>=1.12
Provides-Extra: diazo
Requires-Dist: diazo>=1.0.5; extra == "diazo"
Requires-Dist: lxml>=3.4; extra == "diazo"
Provides-Extra: tests
Requires-Dist: diazo; extra == "tests"
Requires-Dist: lxml>=3.4; extra == "tests"
Requires-Dist: coverage; extra == "tests"
Requires-Dist: flake8; extra == "tests"
